pymatsolver/__init__.py
pymatsolver/direct.py
pymatsolver/iterative.py
pymatsolver/solvers.py
pymatsolver/wrappers.py
pymatsolver/mumps/__init__.py
pymatsolver-0.1.2.dist-info/DESCRIPTION.rst
pymatsolver-0.1.2.dist-info/METADATA
pymatsolver-0.1.2.dist-info/RECORD
pymatsolver-0.1.2.dist-info/WHEEL
pymatsolver-0.1.2.dist-info/metadata.json
pymatsolver-0.1.2.dist-info/top_level.txt
tests/__init__.py
tests/test_Basic.py
tests/test_BicgJacobi.py
tests/test_Mumps.py
tests/test_Pardiso.py
tests/test_Scipy.py
tests/test_Triangle.py
