Metadata-Version: 2.0
Name: pymatsolver
Version: 0.1.2
Summary: pymatsolver: Matrix Solvers for Python
Home-page: http://simpeg.xyz/
Author: Rowan Cockett
Author-email: rowanc1@gmail.com
License: MIT
Download-URL: http://github.com/rowanc1/pymatsolver
Keywords: matrix solver
Platform: Windows
Platform: Linux
Platform: Solaris
Platform: Mac OS-X
Platform: Unix
Classifier: Development Status :: 4 - Beta
Classifier: Intended Audience :: Developers
Classifier: Intended Audience :: Science/Research
Classifier: License :: OSI Approved :: MIT License
Classifier: Programming Language :: Python
Classifier: Topic :: Scientific/Engineering
Classifier: Topic :: Scientific/Engineering :: Mathematics
Classifier: Topic :: Scientific/Engineering :: Physics
Classifier: Operating System :: Microsoft :: Windows
Classifier: Operating System :: POSIX
Classifier: Operating System :: Unix
Classifier: Operating System :: MacOS
Classifier: Natural Language :: English
Requires-Dist: numpy (>=1.7)
Requires-Dist: pyMKL (>=0.0.3)
Requires-Dist: scipy (>=0.13)
